elara/__init__.py
elara/converter.py
elara/fileutils.py
elara/highlighter.py
elara/main.py
elara/notebook.py
elara/samples/colab.html
elara/samples/colab.ipynb
elara/samples/mine.html
elara/samples/mine.ipynb
elara/schema_validator.py
elara/schemas/v4.0.json
elara/template_renderer.py
elara/templates/export.html
elara/test.html
elara/themes/latte.json
elara/themes/vin-theme.json
elara/themes.py
elarapy-0.1.1.dist-info/LICENSE.txt
elarapy-0.1.1.dist-info/METADATA
elarapy-0.1.1.dist-info/WHEEL
elarapy-0.1.1.dist-info/entry_points.txt
elarapy-0.1.1.dist-info/RECORD
